README.md
setup.py
word_polysemy/__init__.py
word_polysemy/average.py
word_polysemy/load_csv.py
word_polysemy/main.py
word_polysemy/sum.py
word_polysemy/top_ten.py
word_polysemy.egg-info/PKG-INFO
word_polysemy.egg-info/SOURCES.txt
word_polysemy.egg-info/dependency_links.txt
word_polysemy.egg-info/requires.txt
word_polysemy.egg-info/top_level.txt
word_polysemy/plots/__init__.py
word_polysemy/plots/visualization.py