Metadata-Version: 1.1
Name: word-polysemy
Version: 1.0.0
Summary: Get the polysemy of each word
Home-page: https://github.com/cristinafareizaga/word_polysemy.git
Author: Cristina Areizaga
Author-email: cristinafareizaga@gmail.com
License: UNKNOWN
Platform: UNKNOWN
Classifier: Programming Language :: Python :: 3
Classifier: License :: OSI Approved :: MIT License
